setup.py
SBISToolkit.egg-info/PKG-INFO
SBISToolkit.egg-info/SOURCES.txt
SBISToolkit.egg-info/dependency_links.txt
SBISToolkit.egg-info/requires.txt
SBISToolkit.egg-info/top_level.txt
sbis_toolkit/__init__.py
sbis_toolkit/config.ini
sbis_toolkit/bl_methods/__init__.py
sbis_toolkit/bl_methods/docs.py
sbis_toolkit/git_sbis/__init__.py
sbis_toolkit/git_sbis/git_sbis.py
sbis_toolkit/utils/__init__.py
sbis_toolkit/utils/converting.py
sbis_toolkit/utils/hooks.py
sbis_toolkit/utils/rpc_client.py