Metadata-Version: 1.0
Name: SBISToolkit
Version: 1.4
Summary: SBIS Python dev toolkit.
Home-page: UNKNOWN
Author: Vladislav Vasyuk
Author-email: nazgarth@gmail.com
License: UNKNOWN
Platform: UNKNOWN
